mhfp/__init__.py
mhfp/encoder.py
mhfp/lsh_forest.py
mhfp-1.9.6.dist-info/LICENSE
mhfp-1.9.6.dist-info/METADATA
mhfp-1.9.6.dist-info/WHEEL
mhfp-1.9.6.dist-info/top_level.txt
mhfp-1.9.6.dist-info/RECORD
