Metadata-Version: 2.1
Name: mhfp
Version: 1.9.6
Summary: Molecular MHFP fingerprints for cheminformatics applications
Home-page: https://github.com/reymond-group/mhfp
Author: Daniel Probst
License-File: LICENSE
Provides-Extra: dev
Requires-Dist: pytest ; extra == 'dev'
